ebat/__init__.py
ebat/sample_authenticator.py
ebat/data/__init__.py
ebat/data/suppliers.py
ebat/evaluation/__init__.py
ebat/evaluation/evaluator.py
ebat/evaluation/metrics/__init__.py
ebat/evaluation/metrics/biometric_information.py
ebat/evaluation/metrics/frequency_count_of_scores.py
ebat/evaluation/metrics/gini_coefficient.py
ebat-0.2.8.dist-info/METADATA
ebat-0.2.8.dist-info/WHEEL
ebat-0.2.8.dist-info/licenses/LICENSE
ebat-0.2.8.dist-info/licenses/NOTICE
ebat-0.2.8.dist-info/RECORD
