Metadata-Version: 2.4
Name: ebat
Version: 0.2.8
Summary: EBAT: Evaluation of Behaviuoral Authentication Toolbox
Project-URL: Homepage, https://code.europa.eu/ebat/ebat
Project-URL: Issues, https://code.europa.eu/ebat/ebat/-/issues
Author-email: Andraž Krašovec <andraz.krasovec@ec.europa.eu>
License-File: LICENSE
License-File: NOTICE
Classifier: Development Status :: 3 - Alpha
Classifier: Intended Audience :: Science/Research
Classifier: License :: OSI Approved :: European Union Public Licence 1.2 (EUPL 1.2)
Classifier: Operating System :: OS Independent
Classifier: Programming Language :: Python :: 3
Classifier: Topic :: Security
Requires-Python: >=3.8
